kaggleease/__init__.py
kaggleease/auth.py
kaggleease/cache.py
kaggleease/cli.py
kaggleease/client.py
kaggleease/errors.py
kaggleease/load.py
kaggleease/magics.py
kaggleease/progress.py
kaggleease/search.py
kaggleease-1.3.9.dist-info/licenses/LICENSE
kaggleease-1.3.9.dist-info/METADATA
kaggleease-1.3.9.dist-info/WHEEL
kaggleease-1.3.9.dist-info/entry_points.txt
kaggleease-1.3.9.dist-info/top_level.txt
kaggleease-1.3.9.dist-info/RECORD
