Metadata-Version: 2.4
Name: kaggleease
Version: 1.3.9
Summary: The fastest, notebook-first way to load Kaggle datasets into pandas with one line.
Author: KaggleEase Contributors
License: MIT License
Project-URL: Homepage, https://github.com/Dinesh-raya/kaagleease
Project-URL: Repository, https://github.com/Dinesh-raya/kaagleease
Project-URL: Documentation, https://github.com/Dinesh-raya/kaagleease#readme
Classifier: Development Status :: 4 - Beta
Classifier: Intended Audience :: Developers
Classifier: Intended Audience :: Science/Research
Classifier: License :: OSI Approved :: MIT License
Classifier: Programming Language :: Python :: 3
Classifier: Programming Language :: Python :: 3.7
Classifier: Programming Language :: Python :: 3.8
Classifier: Programming Language :: Python :: 3.9
Classifier: Programming Language :: Python :: 3.10
Classifier: Programming Language :: Python :: 3.11
Classifier: Topic :: Scientific/Engineering :: Information Analysis
Classifier: Topic :: Software Development :: Libraries :: Python Modules
Requires-Python: >=3.7
License-File: LICENSE
Requires-Dist: click>=7.0
Requires-Dist: ipython>=7.0.0
Requires-Dist: kagglehub>=0.1.0
Requires-Dist: pandas>=1.0.0
Requires-Dist: pyarrow>=1.0.0
Requires-Dist: requests>=2.25.0
Requires-Dist: psutil>=5.0.0
Provides-Extra: dev
Requires-Dist: pytest>=6.0; extra == "dev"
Requires-Dist: black>=21.0; extra == "dev"
Requires-Dist: flake8>=3.8; extra == "dev"
Dynamic: license-file
